randomstate/__init__.py
randomstate/_deprecated.py
randomstate/_version.py
randomstate/aligned_malloc.c
randomstate/aligned_malloc.h
randomstate/aligned_malloc.pxi
randomstate/array_fillers.pxi
randomstate/array_fillers.pxi.in
randomstate/array_utilities.pxi
randomstate/binomial.pxd
randomstate/bounded_integers.pxi
randomstate/bounded_integers.pxi.in
randomstate/compat.py
randomstate/config.pxi
randomstate/defaults.pxi
randomstate/distributions.c
randomstate/distributions.h
randomstate/dsfmt-config.pxi
randomstate/dsfmt.c
randomstate/dsfmt.pyx
randomstate/entropy.c
randomstate/entropy.pyd
randomstate/entropy.pyx
randomstate/mlfg_1279_861-config.pxi
randomstate/mlfg_1279_861.c
randomstate/mlfg_1279_861.pyx
randomstate/mrg32k3a-config.pxi
randomstate/mrg32k3a.c
randomstate/mrg32k3a.pyx
randomstate/mt19937-config.pxi
randomstate/mt19937.c
randomstate/mt19937.pyx
randomstate/pcg32-config.pxi
randomstate/pcg32.c
randomstate/pcg32.pyx
randomstate/pcg64-config.pxi
randomstate/pcg64.c
randomstate/pcg64.pyx
randomstate/performance.py
randomstate/randomstate.pyx
randomstate/setup-single-rng.py
randomstate/sfmt-config.pxi
randomstate/sfmt.c
randomstate/sfmt.pyx
randomstate/xoroshiro128plus-config.pxi
randomstate/xoroshiro128plus.c
randomstate/xoroshiro128plus.pyx
randomstate/xorshift1024-config.pxi
randomstate/xorshift1024.c
randomstate/xorshift1024.pyx
randomstate/xorshift128-config.pxi
randomstate/xorshift128.c
randomstate/xorshift128.pyx
randomstate/ziggurat.h
randomstate/ziggurat_constants.h
randomstate/interface/dSFMT/dSFMT-poly.h
randomstate/interface/dSFMT/dSFMT-shim.c
randomstate/interface/dSFMT/dSFMT-shim.h
randomstate/interface/dSFMT/dSFMT.pxi
randomstate/interface/mlfg-1279-861/mlfg-1279-861-shim.c
randomstate/interface/mlfg-1279-861/mlfg-1279-861-shim.h
randomstate/interface/mlfg-1279-861/mlfg-1279-861.pxi
randomstate/interface/mrg32k3a/mrg32k3a-shim.c
randomstate/interface/mrg32k3a/mrg32k3a-shim.h
randomstate-1.14.0.dist-info/DESCRIPTION.rst
randomstate-1.14.0.dist-info/METADATA
randomstate-1.14.0.dist-info/RECORD
randomstate-1.14.0.dist-info/WHEEL
randomstate-1.14.0.dist-info/metadata.json
randomstate-1.14.0.dist-info/top_level.txt
