Metadata-Version: 2.0
Name: randomstate
Version: 1.14.0
Summary: Next-gen RandomState supporting multiple PRNGs
Home-page: https://github.com/bashtage/ng-numpy-randomstate
Author: Kevin Sheppard
Author-email: kevin.k.sheppard@gmail.com
License: NSCA
Keywords: pseudo random numbers,PRNG,RNG,RandomState,random,random numbers,parallel random numbers,PCG,XorShift,dSFMT,MT19937
Platform: UNKNOWN
Classifier: Development Status :: 5 - Production/Stable
Classifier: Environment :: Console
Classifier: Intended Audience :: End Users/Desktop
Classifier: Intended Audience :: Financial and Insurance Industry
Classifier: Intended Audience :: Information Technology
Classifier: Intended Audience :: Science/Research
Classifier: License :: OSI Approved
Classifier: Operating System :: MacOS :: MacOS X
Classifier: Operating System :: Microsoft :: Windows
Classifier: Operating System :: POSIX :: Linux
Classifier: Operating System :: Unix
Classifier: Programming Language :: C
Classifier: Programming Language :: Cython
Classifier: Programming Language :: Python :: 2.7
Classifier: Programming Language :: Python :: 3.3
Classifier: Programming Language :: Python :: 3.4
Classifier: Programming Language :: Python :: 3.5
Classifier: Programming Language :: Python :: 3.6
Classifier: Topic :: Adaptive Technologies
Classifier: Topic :: Artistic Software
Classifier: Topic :: Office/Business :: Financial
Classifier: Topic :: Scientific/Engineering
Classifier: Topic :: Security :: Cryptography
